{
  "slug": "doerfler-ag",
  "recorder": "take4_event_logged_v2_offsets",
  "generated_at": "2026-05-31T18:08:12.559Z",
  "part_webm_offsets": {
    "1": 13.309999999999999,
    "3": 0.26399999999999996,
    "4": 2.4090000000000003,
    "5": 0.131,
    "6": 0,
    "7": 6.656000000000001
  },
  "events": [
    {
      "part": 1,
      "name": "part_start",
      "recording_t": 0
    },
    {
      "part": 1,
      "name": "recording_start",
      "recording_t": 0
    },
    {
      "part": 1,
      "name": "dashboard_visible",
      "recording_t": 13.61
    },
    {
      "part": 1,
      "name": "case_click",
      "recording_t": 22.922
    },
    {
      "part": 1,
      "name": "case_initial_neu_visible",
      "recording_t": 25.42
    },
    {
      "part": 1,
      "name": "status_dropdown_open",
      "recording_t": 31.945
    },
    {
      "part": 1,
      "name": "termin_versenden_btn_visible",
      "recording_t": 82.07
    },
    {
      "part": 1,
      "name": "inarbeit_view_visible",
      "recording_t": 103.41
    },
    {
      "part": 2,
      "name": "part_start",
      "recording_t": 0
    },
    {
      "part": 2,
      "name": "cut_start",
      "recording_t": 0
    },
    {
      "part": 2,
      "name": "cut_end",
      "recording_t": 1.499
    },
    {
      "part": 3,
      "name": "part_start",
      "recording_t": 0
    },
    {
      "part": 3,
      "name": "phone_day1_start",
      "recording_t": 0
    },
    {
      "part": 3,
      "name": "phone_homescreen_visible",
      "recording_t": 0.564
    },
    {
      "part": 3,
      "name": "sms_notif_visible",
      "recording_t": 2.773
    },
    {
      "part": 3,
      "name": "sms_thread_opened",
      "recording_t": 3.587
    },
    {
      "part": 3,
      "name": "phone_day1_end",
      "recording_t": 6.792
    },
    {
      "part": 4,
      "name": "part_start",
      "recording_t": 0
    },
    {
      "part": 4,
      "name": "recording_start",
      "recording_t": 0
    },
    {
      "part": 4,
      "name": "inarbeit_view_post_visible",
      "recording_t": 2.709
    },
    {
      "part": 4,
      "name": "bearbeiten2_click",
      "recording_t": 7.311
    },
    {
      "part": 4,
      "name": "status_dropdown2_open",
      "recording_t": 8.327
    },
    {
      "part": 4,
      "name": "status_erledigt_set",
      "recording_t": 10.763
    },
    {
      "part": 4,
      "name": "erledigt_speichern_click",
      "recording_t": 11.215
    },
    {
      "part": 4,
      "name": "bewertung_pre_visible",
      "recording_t": 13.284
    },
    {
      "part": 4,
      "name": "bewertung_anfragen_click",
      "recording_t": 15.848
    },
    {
      "part": 4,
      "name": "akt2_end",
      "recording_t": 32.201
    },
    {
      "part": 5,
      "name": "part_start",
      "recording_t": 0
    },
    {
      "part": 5,
      "name": "phone_day2_start",
      "recording_t": 0
    },
    {
      "part": 5,
      "name": "phone_sms_thread_visible",
      "recording_t": 0.431
    },
    {
      "part": 5,
      "name": "phone_day2_end",
      "recording_t": 5.445
    },
    {
      "part": 6,
      "name": "part_start",
      "recording_t": 0
    },
    {
      "part": 6,
      "name": "review_start",
      "recording_t": 0
    },
    {
      "part": 6,
      "name": "rating_intro_visible",
      "recording_t": 3.809
    },
    {
      "part": 6,
      "name": "rating_stars_clicked",
      "recording_t": 4.758
    },
    {
      "part": 6,
      "name": "rating_submit_click",
      "recording_t": 10.761
    },
    {
      "part": 6,
      "name": "review_done_visible",
      "recording_t": 14.476
    },
    {
      "part": 7,
      "name": "part_start",
      "recording_t": 0
    },
    {
      "part": 7,
      "name": "closing_start",
      "recording_t": 0
    },
    {
      "part": 7,
      "name": "case_review_done_visible",
      "recording_t": 6.956
    },
    {
      "part": 7,
      "name": "dashboard_final_visible",
      "recording_t": 13.814
    },
    {
      "part": 7,
      "name": "closing_end",
      "recording_t": 20.829
    }
  ]
}